Metadata-Version: 2.1
Name: ilus
Version: 2.0.0
Summary: ilus: A handy tools for generating WGS/WES analysis pipeline.
Home-page: https://github.com/ShujiaHuang/ilus
Author: Shujia Huang
Author-email: huangshujia9@gmail.com
Maintainer: Shujia Huang
Maintainer-email: huangshujia9@gmail.com
License: BSD (3-clause)
Download-URL: https://github.com/ShujiaHuang/ilus
Platform: UNKNOWN
Classifier: License :: OSI Approved :: BSD License
Classifier: Intended Audience :: Science/Research
Classifier: Programming Language :: Python :: 3.6
Classifier: Programming Language :: Python :: 3.7
Classifier: Programming Language :: Python :: 3.8
Classifier: Programming Language :: Python :: 3.9
Classifier: Programming Language :: Python :: 3.10
Classifier: Programming Language :: Python :: 3.11
Classifier: Topic :: Scientific/Engineering :: Bio-Informatics
Classifier: Operating System :: POSIX
Classifier: Operating System :: POSIX :: Linux
Classifier: Operating System :: MacOS
Requires-Python: >=3.5
License-File: LICENSE
